pyofilename-0.1.0.dist-info/METADATA
pyofilename-0.1.0.dist-info/WHEEL
pyofilename/__init__.py
pyofilename/__init__.pyi
pyofilename/pyofilename.cpython-310-x86_64-linux-gnu.so
pyofilename-0.1.0.dist-info/RECORD
