Metadata-Version: 2.1
Name: pyofilename
Version: 0.1.0
Classifier: Programming Language :: Rust
Classifier: Programming Language :: Python :: Implementation :: CPython
Classifier: Programming Language :: Python :: Implementation :: PyPy
Summary: Windows-proof safe file name generator.
Keywords: file,filename
Author: ilotoki0804 <ilotoki0804@gmail.com>
Author-email: ilotoki0804 <ilotoki0804@gmail.com>
License: MIT License
Requires-Python: >=3.8
